motass/__init__.py
motass/__main__.py
motass/inc/json/dict_tracy.json
motass-0.0.1.dist-info/LICENSE
motass-0.0.1.dist-info/METADATA
motass-0.0.1.dist-info/WHEEL
motass-0.0.1.dist-info/entry_points.txt
motass-0.0.1.dist-info/top_level.txt
motass-0.0.1.dist-info/RECORD
