Metadata-Version: 2.1
Name: motass
Version: 0.0.1
Summary: Một API Simple Site
Author-email: Mike Steele <mike@mikesteele.us>
License: MIT License
Project-URL: Homepage, https://github.com/soulrx/motass
Keywords: database,fetch,db
Classifier: License :: OSI Approved :: MIT License
Classifier: Programming Language :: Python
Classifier: Programming Language :: Python :: 3
Requires-Python: >=3.10
License-File: LICENSE
Requires-Dist: tomli (>=2.0.1)
Requires-Dist: click (>=8.1.3)
Provides-Extra: dev
Requires-Dist: bumpver ; extra == 'dev'
Requires-Dist: isort ; extra == 'dev'
Requires-Dist: pip-tools ; extra == 'dev'
Requires-Dist: pytest ; extra == 'dev'
